odoo10_addon_l10n_ca_states_translations-10.0.0.1.0.99.dev3-py2.7-nspkg.pth
odoo/addons/l10n_ca_states_translations/README.rst
odoo/addons/l10n_ca_states_translations/__init__.py
odoo/addons/l10n_ca_states_translations/__manifest__.py
odoo/addons/l10n_ca_states_translations/i18n/fr.po
odoo/addons/l10n_ca_states_translations/i18n/l10n_ca_states_translations.pot
odoo/addons/l10n_ca_states_translations/static/description/icon.png
odoo10_addon_l10n_ca_states_translations-10.0.0.1.0.99.dev3.dist-info/DESCRIPTION.rst
odoo10_addon_l10n_ca_states_translations-10.0.0.1.0.99.dev3.dist-info/METADATA
odoo10_addon_l10n_ca_states_translations-10.0.0.1.0.99.dev3.dist-info/RECORD
odoo10_addon_l10n_ca_states_translations-10.0.0.1.0.99.dev3.dist-info/WHEEL
odoo10_addon_l10n_ca_states_translations-10.0.0.1.0.99.dev3.dist-info/metadata.json
odoo10_addon_l10n_ca_states_translations-10.0.0.1.0.99.dev3.dist-info/namespace_packages.txt
odoo10_addon_l10n_ca_states_translations-10.0.0.1.0.99.dev3.dist-info/top_level.txt
